core/__init__.py
core/quiz_main.py
core/quiz_main_testcopy.py
core/quiz_methods.py
core/quiz_methods_testcopy.py
network/__init__.py
network/network_demonstration.py
network/translation.py
network/webscraping.py
unittesting/TestQuizCoreOne.py
unittesting/TestQuizCoreTwo.py
unittesting/__init__.py
unittesting/quiz_main_testing.py
unittesting/quiz_methods_testing.py
unittesting/translation_testing.py
unittesting/unittest_suite.py
unittesting/webscraping_testing.py
py_quizlet_cram_stepthree-0.1.dist-info/METADATA
py_quizlet_cram_stepthree-0.1.dist-info/WHEEL
py_quizlet_cram_stepthree-0.1.dist-info/top_level.txt
py_quizlet_cram_stepthree-0.1.dist-info/RECORD
