Metadata-Version: 2.1
Name: py_quizlet_cram_stepthree
Version: 0.1
Summary: A package for taking quizlet and cram quizzes
Home-page: https://github.com/jonahedmundson/py_quizlet_cram_stepthree/tree/main
Author: Jonah Edmunson and Matthew Yau
Author-email: jonahedmundson@gmail.com
License: MIT
Platform: UNKNOWN
